yearmaps/__init__.py
yearmaps/__main__.py
yearmaps/constant.py
yearmaps/impl/__init__.py
yearmaps/impl/provider.py
yearmaps/impl/task.py
yearmaps/interface/__init__.py
yearmaps/interface/provider.py
yearmaps/provider/BBDCProvider.py
yearmaps/provider/BilibiliProvider.py
yearmaps/provider/CodeforcesProvider.py
yearmaps/provider/GitHubProvider.py
yearmaps/provider/MiFitProvider.py
yearmaps/provider/__init__.py
yearmaps/script.py
yearmaps/server.py
yearmaps/static/asset-manifest.json
yearmaps/static/favicon.ico
yearmaps/static/index.html
yearmaps/static/logo192.png
yearmaps/static/logo512.png
yearmaps/static/manifest.json
yearmaps/static/robots.txt
yearmaps/static/static/css/main.bd7abe2c.css
yearmaps/static/static/css/main.bd7abe2c.css.map
yearmaps/static/static/js/main.8aea6f30.js
yearmaps/static/static/js/main.8aea6f30.js.LICENSE.txt
yearmaps/static/static/js/main.8aea6f30.js.map
yearmaps/utils/__init__.py
yearmaps/utils/colormap.py
yearmaps/utils/colors.py
yearmaps/utils/error.py
yearmaps/utils/file.py
yearmaps/utils/type.py
yearmaps/utils/util.py
yearmaps-0.2.0.dist-info/entry_points.txt
yearmaps-0.2.0.dist-info/LICENSE
yearmaps-0.2.0.dist-info/WHEEL
yearmaps-0.2.0.dist-info/METADATA
yearmaps-0.2.0.dist-info/RECORD
