Metadata-Version: 2.1
Name: yearmaps
Version: 0.2.0
Summary: Generate heat map of a year.
Home-page: https://github.com/zxilly/yearmaps
License: GPL-3.0-only
Author: Zxilly
Author-email: zxilly@outlook.com
Requires-Python: >=3.8,<4.0
Classifier: Development Status :: 4 - Beta
Classifier: License :: OSI Approved :: GNU General Public License v3 (GPLv3)
Classifier: Natural Language :: Chinese (Simplified)
Classifier: Operating System :: OS Independent
Classifier: Programming Language :: Python :: 3
Classifier: Programming Language :: Python :: 3.10
Classifier: Programming Language :: Python :: 3.8
Classifier: Programming Language :: Python :: 3.9
Requires-Dist: PyYAML (>=6.0,<7.0)
Requires-Dist: click (>=8.0.3,<9.0.0)
Requires-Dist: index.py (>=0.21.11,<0.22.0)
Requires-Dist: matplotlib (>=3.5.1,<4.0.0)
Requires-Dist: numpy (>=1.22.1,<2.0.0)
Requires-Dist: requests (>=2.27.1,<3.0.0)
Requires-Dist: schedule (>=1.1.0,<2.0.0)
Requires-Dist: uvicorn (>=0.17.0,<0.18.0)
Project-URL: Bug Tracker, https://github.com/Zxilly/yearmaps/issues
Project-URL: Repository, https://github.com/zxilly/yearmaps
